{
  "index": 174,
  "source_file": "IMG20260707204548.jpg",
  "extracted_at": "2026-07-08T20:51:45.552Z",
  "page_type": "reading",
  "book_series": "Fiesta di idioma",
  "grade": "3",
  "theme": "null",
  "week": "Siman 1",
  "section": "Mi por lesa",
  "page_numbers": [
    "1"
  ],
  "words": [],
  "phrases": [],
  "conversation_rules": [],
  "grammar_rules": [],
  "paragraphs": [
    "Ku ta kue bèk",
    "Hende a kue bèk di bèk. E ta bèk ku ta bèk di bèk. E ta bèk ku ta bèk di bèk.",
    "Ku ta bèk di bèk.",
    "E ta bèk ku ta bèk di bèk.",
    "Ku ta bèk di bèk.",
    "E ta bèk ku ta bèk di bèk.",
    "Ku ta bèk di bèk.",
    "E ta bèk ku ta bèk di bèk.",
    "Ku ta bèk di bèk.",
    "E ta bèk ku ta bèk di bèk."
  ],
  "questions": [
    "Kiko a kue?",
    "Kiko a bèk?",
    "Kiko a bèk di bèk?"
  ],
  "raw_text": "Ku ta kue bèk\nHende a kue bèk di bèk. E ta bèk ku ta bèk di bèk. E ta bèk ku ta bèk di bèk.\nKu ta bèk di bèk.\nE ta bèk ku ta bèk di bèk.\nKu ta bèk di bèk.\nE ta bèk ku ta bèk di bèk.\nKu ta bèk di bèk.\nE ta bèk ku ta bèk di bèk.\nKu ta bèk di bèk.\nE ta bèk ku ta bèk di bèk.\n\nKiko a kue?\nKiko a bèk?\nKiko a bèk di bèk?"
}