{
  "index": 231,
  "source_file": "IMG20260707210024.jpg",
  "extracted_at": "2026-07-08T21:08:45.680Z",
  "page_type": "other",
  "book_series": "Fiesta di idioma",
  "grade": "3",
  "theme": "Tema 6 Vários kambio importante",
  "week": "Siman 3",
  "section": null,
  "page_numbers": [
    "30"
  ],
  "words": [],
  "phrases": [
    "Buska e palabra ku ta kuadra.",
    "Skibi e nòmber di e frase ku e palabra ku ta skèr.",
    "Mené a drenta klas i...",
    "Kiko e invento?",
    "E tin ku inventa ku ta masha òrdi.",
    "Bo a kontestá?",
    "Kiko e invento?",
    "E tin ku inventa ku ta masha òrdi."
  ],
  "conversation_rules": [],
  "grammar_rules": [],
  "paragraphs": [
    "5 Pensa bon",
    "5! Yena pronòmber personal",
    "Pronòmber personal",
    "Un pronòmber personal ta un lugá di e nòmber di un persona, un animal, of un cosa.",
    "E pronòmber personal singular: i ta: nos, bos/bosnan/bosonan i nan.",
    "E pronòmber personal plural ta: nos, bos/bosnan/bosonan i nan.",
    "Yena e pronòmber personal den e siguiente frasen.",
    "Mené a drenta klas i...",
    "Kiko e invento?",
    "E tin ku inventa ku ta masha òrdi.",
    "Bo a kontestá?",
    "Kiko e invento?",
    "E tin ku inventa ku ta masha òrdi."
  ],
  "questions": [],
  "raw_text": "5 Pensa bon\n\n5! Yena pronòmber personal\n\nPronòmber personal\nUn pronòmber personal ta un lugá di e nòmber di un persona, un animal, of un cosa.\nE pronòmber personal singular: i ta: nos, bos/bosnan/bosonan i nan.\nE pronòmber personal plural ta: nos, bos/bosnan/bosonan i nan.\nYena e pronòmber personal den e siguiente frasen.\nMené a drenta klas i...\nKiko e invento?\nE tin ku inventa ku ta masha òrdi.\nBo a kontestá?\nKiko e invento?\nE tin ku inventa ku ta masha òrdi."
}