{
  "index": 397,
  "source_file": "IMG20260709151421.jpg",
  "book_role": "teacher",
  "extracted_at": "2026-07-10T03:03:27.907Z",
  "page_type": "teacher_guide",
  "book_series": "Fiesta di idioma",
  "grade": "6",
  "theme": "Tema 6",
  "week": null,
  "section": "methodology",
  "page_numbers": [
    "36",
    "37"
  ],
  "words": [],
  "phrases": [
    "Alumno ta komprendé ku ta trata di un kuenta realista.",
    "Alumno ta amplia profundidat su vocabulario.",
    "Alumno ta komprendé relashon entre palabra."
  ],
  "conversation_rules": [],
  "grammar_rules": [],
  "lesson_objectives": [
    "Alumno ta por hasi un pregunta.",
    "Alumno ta por komprendé relashon entre palabra."
  ],
  "teaching_notes": [
    "Esplicá Marco Polo pa pas di tema.",
    "Punta: E ta dishe ku Marco Polo ta un persona ku a bini di un otro pais.",
    "E ta komprendé ku ta trata di un kuenta realista.",
    "E ta por hasi un pregunta."
  ],
  "orthography_teaching": [],
  "methodology": [
    "Hasi e promé frase hunto ku muchanan.",
    "Punta: E ta dishe ku Marco Polo ta un persona ku a bini di un otro pais.",
    "E ta komprendé ku ta trata di un kuenta realista."
  ],
  "paragraphs": [],
  "questions": [],
  "raw_text": "4 Vokabulario\nMarco Polo\nMeta\nAlumno ta komprendé ku ta trata di un kuenta realista.\nAlumno ta komprendé relashon entre palabra.\nAlumno ta amplia profundidat su vocabulario.\n\nMaterial\n• Fiesta di idioma C2, página 26-29\n• Skèf\n\nIntrodukshon\n• Esplicá Marco Polo pa pas di tema.\n• Punta: E ta dishe ku Marco Polo ta un persona ku a bini di un otro pais.\n• E ta komprendé ku ta trata di un kuenta realista.\n• E ta por hasi un pregunta.\n\nKontesta\n• Taréa 1\n• Taréa 2\n\n5 Pensa bon\nSi Pone e palabran den e rei korekto\nMeta\nAlumno ta por dishe ku Marco Polo ta un persona ku a bini di un otro pais.\nAlumno ta komprendé relashon entre palabra.\n\nMaterial\n• Fiesta di idioma C2, página 30\n• Skèf\n\nIntrodukshon\n• Hasi e promé frase hunto ku muchanan.\n• Punta: E ta dishe ku Marco Polo ta un persona ku a bini di un otro pais.\n• E ta komprendé ku ta trata di un kuenta realista.\n\nKontesta\n• Taréa 1\n• Taréa 2\n\nRefleksion\n• E alumonan a hala e dislìt kon bo a bisi nan?"
}