{
  "index": 475,
  "source_file": "IMG20260709152016.jpg",
  "book_role": "teacher",
  "extracted_at": "2026-07-10T03:44:44.472Z",
  "page_type": "teacher_guide",
  "book_series": "Fiesta di idioma",
  "grade": "4",
  "theme": "Tema 9",
  "week": "Siman 2",
  "section": "methodology",
  "page_numbers": [
    "136",
    "137"
  ],
  "words": [],
  "phrases": [
    "Alumno ta lesa e teks.",
    "Alumno ta komprendé e teks.",
    "Alumno ta amplia su vokabulario."
  ],
  "conversation_rules": [],
  "grammar_rules": [],
  "lesson_objectives": [
    "Suvini e teks.",
    "Alumno ta komprendé e teks.",
    "Alumno ta amplia su vokabulario."
  ],
  "teaching_notes": [
    "Laga e alumno wak e plachinan nan página 136-137.",
    "Despué di lesa, e alumno por krea un mira.",
    "Lesa e teks i komprondé e teks.",
    "E alumno mester krea un plan di e teks."
  ],
  "orthography_teaching": [],
  "methodology": [
    "E alumno por krea un mira di e teks.",
    "E ta lesa e teks i komprondé.",
    "E ta amplia su vokabulario."
  ],
  "paragraphs": [],
  "questions": [],
  "raw_text": "2 Mi por lesa\nSuvini\nMeta\n• Suvini e teks.\n• Alumno ta komprendé e teks.\n• Alumno ta amplia su vokabulario.\n\nMaterial\n• Fiesta di idioma C2, página 136-137\n\nIntroduhson\nLaga e alumno wak e plachinan nan página 136-137.\n• Despué di lesa, e alumno por krea un mira.\n• Lesa e teks i komprondé e teks.\n• E alumno mester krea un plan di e teks.\n\nInternalisashon\nDespué di lesa e teks. Duna buki binti."
}