{
  "index": 513,
  "source_file": "IMG20260709152255.jpg",
  "book_role": "teacher",
  "extracted_at": "2026-07-10T03:57:00.064Z",
  "page_type": "lesson_plan",
  "book_series": "Fiesta di idioma",
  "grade": "6",
  "theme": "Tema 10",
  "week": "Siman 2",
  "section": "methodology",
  "page_numbers": [
    "181"
  ],
  "words": [],
  "phrases": [
    "Alumno ta komprendé riko di diferente sorto di palabra.",
    "Alumno ta disraya i por komprendé ku tin kefer ku e ta disraya."
  ],
  "conversation_rules": [],
  "grammar_rules": [],
  "lesson_objectives": [
    "Alumno ta komprendé riko di diferente sorto di palabra.",
    "Alumno ta disraya i por komprendé ku tin kefer ku e ta disraya."
  ],
  "teaching_notes": [
    "Duna e alumno un oportunidat pa wak e ta yera e plachi i kiko e ekspreshonan.",
    "Splica ku e teksito chiki ta tokante di un bishita pa e sintimentu.",
    "E ta yera e plachi pa e ta komprendé e frase."
  ],
  "orthography_teaching": [],
  "methodology": [
    "Duna e alumno un oportunidat pa wak e ta yera e plachi i kiko e ekspreshonan.",
    "Splica ku e teksito chiki ta tokante di un bishita pa e sintimentu."
  ],
  "paragraphs": [],
  "questions": [],
  "raw_text": "5h kua palabra bo ta yena?\nMeta\nAlumno ta komprendé riko di diferente sorto di palabra.\nAlumno ta disraya i por komprendé ku tin kefer ku e ta disraya.\n\nMaterial\n• Fiesta di idioma C2, página 181\n• Skerf\n\nIntrodukshon\n• Duna e alumno un oportunidat pa wak e ta yera e plachi i kiko e ekspreshonan.\n• Splica ku e teksito chiki ta tokante di un bishita pa e sintimentu.\n\nKontesta\n1. outpusta\n2. parda di atrakshon\n3. gondola\n4. lampon\n5. manto ruso\n6. kurent di akua\n\nReflekhon\nKon e alumno a haña e frase? Si nan a hule e frase di, ku palabra nan tabata hiba difisil?"
}