{
  "index": 529,
  "source_file": "IMG20260709152429.jpg",
  "book_role": "teacher",
  "extracted_at": "2026-07-10T03:59:35.873Z",
  "page_type": "teacher_guide",
  "book_series": "Fiesta di idioma",
  "grade": "6",
  "theme": "Tema 10",
  "week": "Siman 4",
  "section": "methodology",
  "page_numbers": [
    "286",
    "287"
  ],
  "words": [],
  "phrases": [
    "Alumno ta amplía i profundisá su vocabulario.",
    "E ta komprondé ku ta plachi ku yabi."
  ],
  "conversation_rules": [
    "E ta komprondé ku ta plachi ku yabi."
  ],
  "grammar_rules": [],
  "lesson_objectives": [
    "E ta komprondé ku ta plachi ku yabi.",
    "Alumno ta desaroyá su habilidad metalinésiko."
  ],
  "teaching_notes": [
    "E ta komprondé ku ta plachi ku yabi.",
    "E ta komprondé ku ta plachi ku yabi."
  ],
  "orthography_teaching": [],
  "methodology": [
    "E ta komprondé ku ta plachi ku yabi.",
    "Alumon ta desaroyá su habilidad metalinésiko."
  ],
  "paragraphs": [],
  "questions": [
    "¿Alumon ta konosé e yabinan?"
  ],
  "raw_text": "5 Pensa bon\n\nSin Komparashon\n\nMunto i sôbre i yvna palabra den frase pa hasi un komparashon.\n\nAlumon ta desaroyá su habilidad metalinésiko.\nAlumon ta amplía i profundisá su vocabulario.\n\nMaterial\nFiesta di idioma C2, página 200\n\nIntrodukshon\n\nE ta un meta oal.\nE ta un meta oal.\n\nRefleksion\n\nPa masha ku nan ta halá e tur.\nNan masha sin komparashon.\n\nIntrodukshon\n\nE ta un meta oal.\nE ta un meta oal.\n\nInformashon\n\nE ta un meta oal.\n\nKontesta\n1. 7. mas bôrdó\n2. 1. bôk\n3. 2. bôk\n4. 3. bôk\n5. 4. bôk\n6. 5. bôk\n7. 6. bôk\n8. 7. bôk"
}